arro3/io/__init__.py
arro3/io/_csv.pyi
arro3/io/_io.abi3.so
arro3/io/_io.pyi
arro3/io/_ipc.pyi
arro3/io/_json.pyi
arro3/io/_parquet.pyi
arro3/io/_pyo3_object_store.pyi
arro3/io/py.typed
arro3/io/store.pyi
arro3_io-0.6.4.dist-info/METADATA
arro3_io-0.6.4.dist-info/WHEEL
arro3_io-0.6.4.dist-info/RECORD
